node/__init__.py
node/node.py
node/node_all_letter.py
node/node_and.py
node/node_assign.py
node/node_concat.py
node/node_empty_begin.py
node/node_empty_end.py
node/node_freq.py
node/node_match_text.py
node/node_not_match_text.py
node/node_one_or_not.py
node/node_or.py
node/node_ordered_or.py
node/node_pass.py
node/node_plus.py
node/node_rule_refer.py
node/node_sm_cardinal_int.py
node/node_sm_float.py
node/node_sm_int.py
node/node_trie.py
node/node_var_condition.py
node/node_var_refer.py
node/node_white_space.py
rule/__init__.py
slotminer/__init__.py
slotminer/dict_tree.py
slotminer/extent.py
slotminer/my_trie.py
slotminer/rule_loader.py
slotminer/rule_process.py
slotminer/setup.py
slotminer/sm_queue.py
slotminer/sm_stack.py
slotminer/test.py
slotminer/test_trie.py
slotminer/tree.py
slotminer/trie_loader.py
slotminer/var.py
slotminer/node/__init__.py
slotminer/node/node.py
slotminer/node/node_all_letter.py
slotminer/node/node_and.py
slotminer/node/node_assign.py
slotminer/node/node_concat.py
slotminer/node/node_empty_begin.py
slotminer/node/node_empty_end.py
slotminer/node/node_freq.py
slotminer/node/node_match_text.py
slotminer/node/node_not_match_text.py
slotminer/node/node_one_or_not.py
slotminer/node/node_or.py
slotminer/node/node_ordered_or.py
slotminer/node/node_pass.py
slotminer/node/node_plus.py
slotminer/node/node_rule_refer.py
slotminer/node/node_sm_cardinal_int.py
slotminer/node/node_sm_float.py
slotminer/node/node_sm_int.py
slotminer/node/node_trie.py
slotminer/node/node_var_condition.py
slotminer/node/node_var_refer.py
slotminer/node/node_white_space.py
slotminer/rule/__init__.py
slotminer-0.9.2.dist-info/LICENSE
slotminer-0.9.2.dist-info/METADATA
slotminer-0.9.2.dist-info/WHEEL
slotminer-0.9.2.dist-info/top_level.txt
slotminer-0.9.2.dist-info/RECORD
