Metadata-Version: 2.1
Name: slotminer
Version: 0.9.2
Summary: python package for slot extraction (information extraciton) from texts.
Home-page: https://github.com/bytecell/slotminer
Author: bytecell
Author-email: ysjay@chungbuk.ac.kr
License: UNKNOWN
Platform: UNKNOWN
Classifier: Programming Language :: Python :: 3
Classifier: License :: OSI Approved :: MIT License
Requires-Dist: cython
